{
  "name": "autonomous_mobile_robotics_humble",

  "build": {
    "dockerfile": "../docker/Dockerfile",
    "context": ".."
  },

  "workspaceMount": "source=${localWorkspaceFolder},target=/ros2_ws,type=bind",
  "workspaceFolder": "/ros2_ws",

  "runArgs": [
    "--net=host",
    "--privileged",
    "--gpus=all",

    "--volume=/dev:/dev",

    "-e", "DISPLAY=${localEnv:DISPLAY}",
    "-v", "/tmp/.X11-unix:/tmp/.X11-unix:rw",

    "--group-add=video",
    "--group-add=render"
  ],

  "containerEnv": {
    "NVIDIA_VISIBLE_DEVICES": "all",
    "NVIDIA_DRIVER_CAPABILITIES": "graphics,utility,compute",
    "__GLX_VENDOR_LIBRARY_NAME": "nvidia"
  },

  "remoteUser": "vscode",

  "features": {
    "ghcr.io/devcontainers/features/common-utils:2": {
      "installZsh": true,
      "installOhMyZsh": false
    }
  },

  "postCreateCommand": "echo 'source /opt/ros/humble/setup.bash' >> ~/.bashrc"
}
